{
  "gateways": [
    {
      "gateway_id": "GW01",
      "name": "Farm Gateway North",
      "location": {
        "lat": 13.3392,
        "lon": 74.7461
      },
      "status": "online"
    },
    {
      "gateway_id": "GW02",
      "name": "Farm Gateway South",
      "location": {
        "lat": 13.3365,
        "lon": 74.7429
      },
      "status": "online"
    },
    {
      "gateway_id": "GW03",
      "name": "Municipal Gateway",
      "location": {
        "lat": 13.3408,
        "lon": 74.7493
      },
      "status": "online"
    }
  ],
  "valves": [
    {
      "device_id": "VALVE_001",
      "gateway_id": "GW01",
      "zone": "Municipal_Zone_1",
      "location": {
        "lat": 13.3373,
        "lon": 74.744
      },
      "valve_position": 87,
      "battery_voltage": 12.23,
      "motor_current": 0.4,
      "temperature": 31,
      "signal_strength": -76,
      "status": "open"
    },
    {
      "device_id": "VALVE_002",
      "gateway_id": "GW01",
      "zone": "Municipal_Zone_1",
      "location": {
        "lat": 13.3399,
        "lon": 74.7496
      },
      "valve_position": 13,
      "battery_voltage": 12.4,
      "motor_current": 2.31,
      "temperature": 39,
      "signal_strength": -71,
      "status": "closed"
    },
    {
      "device_id": "VALVE_003",
      "gateway_id": "GW01",
      "zone": "Municipal_Zone_1",
      "location": {
        "lat": 13.3381,
        "lon": 74.7483
      },
      "valve_position": 26,
      "battery_voltage": 11.57,
      "motor_current": 0.65,
      "temperature": 32,
      "signal_strength": -85,
      "status": "closed"
    },
    {
      "device_id": "VALVE_004",
      "gateway_id": "GW01",
      "zone": "Farm_B",
      "location": {
        "lat": 13.3372,
        "lon": 74.7489
      },
      "valve_position": 17,
      "battery_voltage": 11.73,
      "motor_current": 1.99,
      "temperature": 40,
      "signal_strength": -80,
      "status": "closed"
    },
    {
      "device_id": "VALVE_005",
      "gateway_id": "GW01",
      "zone": "Farm_B",
      "location": {
        "lat": 13.3391,
        "lon": 74.7434
      },
      "valve_position": 34,
      "battery_voltage": 12.06,
      "motor_current": 0.74,
      "temperature": 32,
      "signal_strength": -86,
      "status": "open"
    },
    {
      "device_id": "VALVE_006",
      "gateway_id": "GW01",
      "zone": "Municipal_Zone_1",
      "location": {
        "lat": 13.3414,
        "lon": 74.7492
      },
      "valve_position": 49,
      "battery_voltage": 12.77,
      "motor_current": 0.41,
      "temperature": 37,
      "signal_strength": -70,
      "status": "closed"
    },
    {
      "device_id": "VALVE_007",
      "gateway_id": "GW03",
      "zone": "Farm_B",
      "location": {
        "lat": 13.3397,
        "lon": 74.7475
      },
      "valve_position": 54,
      "battery_voltage": 12.21,
      "motor_current": 1.82,
      "temperature": 30,
      "signal_strength": -76,
      "status": "open"
    },
    {
      "device_id": "VALVE_008",
      "gateway_id": "GW03",
      "zone": "Municipal_Zone_1",
      "location": {
        "lat": 13.3395,
        "lon": 74.7493
      },
      "valve_position": 65,
      "battery_voltage": 11.7,
      "motor_current": 0.26,
      "temperature": 33,
      "signal_strength": -76,
      "status": "closed"
    },
    {
      "device_id": "VALVE_009",
      "gateway_id": "GW03",
      "zone": "Farm_A",
      "location": {
        "lat": 13.3393,
        "lon": 74.745
      },
      "valve_position": 5,
      "battery_voltage": 11.61,
      "motor_current": 1.8,
      "temperature": 33,
      "signal_strength": -80,
      "status": "open"
    },
    {
      "device_id": "VALVE_010",
      "gateway_id": "GW03",
      "zone": "Farm_B",
      "location": {
        "lat": 13.3398,
        "lon": 74.7455
      },
      "valve_position": 3,
      "battery_voltage": 11.96,
      "motor_current": 0.82,
      "temperature": 40,
      "signal_strength": -83,
      "status": "closed"
    }
  ]
}